CHANGES.txt
CONTRIBUTORS.txt
LICENSE
README.txt
TAGS
bootstrap.py
buildout.cfg
setup.cfg
setup.py
collective/__init__.py
collective.eggproxy.egg-info/PKG-INFO
collective.eggproxy.egg-info/SOURCES.txt
collective.eggproxy.egg-info/dependency_links.txt
collective.eggproxy.egg-info/entry_points.txt
collective.eggproxy.egg-info/namespace_packages.txt
collective.eggproxy.egg-info/not-zip-safe
collective.eggproxy.egg-info/requires.txt
collective.eggproxy.egg-info/top_level.txt
collective/eggproxy/README.txt
collective/eggproxy/__init__.py
collective/eggproxy/apache_handler.py
collective/eggproxy/config.py
collective/eggproxy/deployment.ini_tmpl
collective/eggproxy/update_script.py
collective/eggproxy/utils.py
collective/eggproxy/wsgi.ini
collective/eggproxy/wsgi.py
collective/eggproxy/tests/__init__.py
collective/eggproxy/tests/test_utils.py
collective/eggproxy/tests/test_wsgi.py