Metadata-Version: 1.0
Name: collective.eggproxy
Version: 0.5.1
Summary: An egg index proxy
Home-page: http://pypi.python.org/pypi/collective.eggproxy
Author: Ingeniweb; current maintainer Reinout van Rees (The Health Agency)
Author-email: reinout@vanrees.org
License: GPL
Keywords: setuptools easy_install index proxy
Platform: UNKNOWN
Classifier: Programming Language :: Python
Classifier: Topic :: Software Development :: Libraries :: Python Modules
